statomata/__init__.py
statomata/abc.py
statomata/anyio.py
statomata/declarative/__init__.py
statomata/declarative/builder.py
statomata/declarative/config.py
statomata/declarative/registry.py
statomata/declarative/state_machine.py
statomata/exception.py
statomata/executor.py
statomata/iterable.py
statomata/py.typed
statomata/sdk.py
statomata/subscriber/__init__.py
statomata/subscriber/logging.py
statomata/subscriber/registry.py
statomata/transition.py
statomata/unary.py
statomata-0.4.3.dist-info/METADATA
statomata-0.4.3.dist-info/WHEEL
statomata-0.4.3.dist-info/licenses/LICENSE
statomata-0.4.3.dist-info/RECORD
