Metadata-Version: 2.4
Name: statomata
Version: 0.4.3
Summary:  a strictly typed, flexible library for building and running state machines in Python
License: MIT
License-File: LICENSE
Keywords: python,automata,fsm,asyncio,finite-state-machine,fsm-library
Author: zerlok
Author-email: danil.troshnev@gmail.com
Requires-Python: >=3.9,<4.0
Classifier: Development Status :: 3 - Alpha
Classifier: Intended Audience :: Developers
Classifier: License :: OSI Approved :: MIT License
Classifier: Operating System :: OS Independent
Classifier: Programming Language :: Python :: 3
Classifier: Programming Language :: Python :: 3.9
Classifier: Programming Language :: Python :: 3.10
Classifier: Programming Language :: Python :: 3.11
Classifier: Programming Language :: Python :: 3.12
Classifier: Programming Language :: Python :: 3.13
Classifier: Programming Language :: Python :: 3.14
Classifier: Topic :: Software Development :: Libraries
Classifier: Typing :: Typed
Provides-Extra: anyio
Requires-Dist: anyio (>=4.12.0,<5.0.0) ; extra == "anyio"
Requires-Dist: typing-extensions (>=4.15.0,<5.0.0)
Project-URL: Homepage, https://github.com/zerlok/statomata
Project-URL: Issues, https://github.com/zerlok/statomata/issues
